pysatSeasons/__init__.py
pysatSeasons/_core.py
pysatSeasons/avg.py
pysatSeasons/occur_prob.py
pysatSeasons/plot.py
pysatSeasons/version.txt
pysatSeasons/tests/__init__.py
pysatSeasons/tests/test_avg.py
pysatSeasons/tests/test_occur_prob.py
pysatSeasons/tests/test_plot.py
pysatSeasons-0.1.2.dist-info/LICENSE
pysatSeasons-0.1.2.dist-info/METADATA
pysatSeasons-0.1.2.dist-info/WHEEL
pysatSeasons-0.1.2.dist-info/top_level.txt
pysatSeasons-0.1.2.dist-info/RECORD
